lndb_setup/__init__.py
lndb_setup/__main__.py
lndb_setup/_check_versions.py
lndb_setup/_clone.py
lndb_setup/_close.py
lndb_setup/_db.py
lndb_setup/_delete.py
lndb_setup/_docs.py
lndb_setup/_exclusion.py
lndb_setup/_info.py
lndb_setup/_init_instance.py
lndb_setup/_load_instance.py
lndb_setup/_migrate.py
lndb_setup/_schema.py
lndb_setup/_set.py
lndb_setup/_settings.py
lndb_setup/_settings_instance.py
lndb_setup/_settings_load.py
lndb_setup/_settings_save.py
lndb_setup/_settings_store.py
lndb_setup/_settings_user.py
lndb_setup/_setup_knowledge.py
lndb_setup/_setup_schema.py
lndb_setup/_setup_user.py
lndb_setup/_storage.py
lndb_setup/_assets/__init__.py
lndb_setup/_migrations/__init__.py
lndb_setup/_migrations/alembic.ini
lndb_setup/_migrations/env.py
lndb_setup/_migrations/script.py.mako
lndb_setup/test/__init__.py
lndb_setup/test/_env.py
lndb_setup/test/_migrations_e2e.py
lndb_setup/test/_migrations_unit.py
lndb_setup/test/_nox.py
lndb_setup/test/nox.py
lndb_setup-0.31.0.dist-info/entry_points.txt
lndb_setup-0.31.0.dist-info/LICENSE
lndb_setup-0.31.0.dist-info/WHEEL
lndb_setup-0.31.0.dist-info/METADATA
lndb_setup-0.31.0.dist-info/RECORD
