Metadata-Version: 2.1
Name: lndb_setup
Version: 0.31.0
Summary: LaminDB setup.
Author-email: Lamin Labs <laminlabs@gmail.com>
Requires-Dist: lnhub_rest==0.3.0
Requires-Dist: lnschema_core>=0.24.1
Requires-Dist: lamin_logger>=0.2.3
Requires-Dist: cloudpathlib
Requires-Dist: sqlmodel>=0.0.8
Requires-Dist: appdirs
Requires-Dist: supabase
Requires-Dist: python-dotenv
Requires-Dist: erdiagram
Requires-Dist: alembic
Requires-Dist: psycopg2-binary
Requires-Dist: pyjwt
Requires-Dist: natsort
Requires-Dist: pandas
Requires-Dist: pytest_alembic==0.9.1
Requires-Dist: boto3==1.24.59
Requires-Dist: botocore==1.27.59
Requires-Dist: fsspec==2023.1.0
Requires-Dist: s3fs
Requires-Dist: gcsfs
Requires-Dist: python-dateutil
Requires-Dist: pre-commit ; extra == "dev"
Requires-Dist: nox ; extra == "dev"
Requires-Dist: pytest>=6.0 ; extra == "test"
Requires-Dist: pytest-cov ; extra == "test"
Requires-Dist: bionty>=0.5.6 ; extra == "test"
Requires-Dist: lnschema_bionty>=0.6.2 ; extra == "test"
Requires-Dist: lnschema_wetlab>=0.11.5 ; extra == "test"
Requires-Dist: lnbfx>=0.7.1 ; extra == "test"
Requires-Dist: cloudpathlib[gs] ; extra == "test"
Requires-Dist: nbproject_test>=0.4.0 ; extra == "test"
Project-URL: Home, https://github.com/laminlabs/lndb-setup
Provides-Extra: dev
Provides-Extra: test
